msb_arch/__init__.py
msb_arch/base/__init__.py
msb_arch/base/basecontainer.py
msb_arch/base/baseentity.py
msb_arch/mega/__init__.py
msb_arch/mega/manipulator.py
msb_arch/super/__init__.py
msb_arch/super/project.py
msb_arch/super/super.py
msb_arch/utils/__init__.py
msb_arch/utils/logging_setup.py
msb_arch/utils/validation.py
msb_arch-0.1.0.dist-info/METADATA
msb_arch-0.1.0.dist-info/WHEEL
msb_arch-0.1.0.dist-info/licenses/LICENSE
msb_arch-0.1.0.dist-info/RECORD
