Metadata-Version: 2.4
Name: msb_arch
Version: 0.1.0
Summary: Mega-Super-Base (MSB) architecture for flexible and extensible Python applications
Project-URL: Homepage, https://github.com/Torward1024/MSB
Project-URL: Documentation, https://github.com/Torward1024/MSB/docs
Project-URL: Repository, https://github.com/Torward1024/MSB
Project-URL: Issues, https://github.com/Torward1024/MSB/issues
Author-email: Alexey Rudnitskiy <almax1024@gmail.com>
License: MSB Software License
License-File: LICENSE
Keywords: architecture,extensible,msb
Classifier: License :: Other/Proprietary License
Classifier: Operating System :: OS Independent
Classifier: Programming Language :: Python :: 3
Requires-Python: >=3.12
